<xml xmlns:o="urn:schemas-microsoft-com:office:office">
 <o:MainFile HRef="../Week8.html"/>
 <o:File HRef="themedata.thmx"/>
 <o:File HRef="colorschememapping.xml"/>
 <o:File HRef="image002.png"/>
 <o:File HRef="image001.png"/>
 <o:File HRef="image006.png"/>
 <o:File HRef="image003.png"/>
 <o:File HRef="image010.png"/>
 <o:File HRef="image005.png"/>
 <o:File HRef="image014.png"/>
 <o:File HRef="image007.png"/>
 <o:File HRef="image018.png"/>
 <o:File HRef="image009.png"/>
 <o:File HRef="image022.png"/>
 <o:File HRef="image011.png"/>
 <o:File HRef="image026.png"/>
 <o:File HRef="image013.png"/>
 <o:File HRef="image030.png"/>
 <o:File HRef="image015.png"/>
 <o:File HRef="image034.png"/>
 <o:File HRef="image017.png"/>
 <o:File HRef="image038.png"/>
 <o:File HRef="image019.png"/>
 <o:File HRef="image042.png"/>
 <o:File HRef="image021.png"/>
 <o:File HRef="image067.png"/>
 <o:File HRef="image023.png"/>
 <o:File HRef="image069.png"/>
 <o:File HRef="image025.png"/>
 <o:File HRef="image071.png"/>
 <o:File HRef="image027.png"/>
 <o:File HRef="image073.png"/>
 <o:File HRef="image029.png"/>
 <o:File HRef="image075.png"/>
 <o:File HRef="image031.png"/>
 <o:File HRef="image077.png"/>
 <o:File HRef="image033.png"/>
 <o:File HRef="image079.png"/>
 <o:File HRef="image035.png"/>
 <o:File HRef="image081.png"/>
 <o:File HRef="image037.png"/>
 <o:File HRef="image083.png"/>
 <o:File HRef="image039.png"/>
 <o:File HRef="image085.png"/>
 <o:File HRef="image041.png"/>
 <o:File HRef="image087.png"/>
 <o:File HRef="image043.png"/>
 <o:File HRef="filelist.xml"/>
</xml>